fw_gear_dicom_fixer/__init__.py
fw_gear_dicom_fixer/fixers.py
fw_gear_dicom_fixer/main.py
fw_gear_dicom_fixer/metadata.py
fw_gear_dicom_fixer/parser.py
fw_gear_dicom_fixer/utils.py
fw_gear_dicom_fixer/standard/editions.html
fw_gear_dicom_fixer/standard/editions.json
fw_gear_dicom_fixer/standard/2022d/docbook/part03.xml
fw_gear_dicom_fixer/standard/2022d/docbook/part04.xml
fw_gear_dicom_fixer/standard/2022d/docbook/part06.xml
fw_gear_dicom_fixer/standard/2022d/json/dict_info.json
fw_gear_dicom_fixer/standard/2022d/json/iod_info.json
fw_gear_dicom_fixer/standard/2022d/json/module_info.json
fw_gear_dicom_fixer/standard/2022d/json/uid_info.json
fw_gear_dicom_fixer/standard/2022d/json/version
fw_gear_dicom_fixer/standard/2023a/docbook/part03.xml
fw_gear_dicom_fixer/standard/2023a/docbook/part04.xml
fw_gear_dicom_fixer/standard/2023a/docbook/part06.xml
fw_gear_dicom_fixer/standard/2023a/json/dict_info.json
fw_gear_dicom_fixer/standard/2023a/json/iod_info.json
fw_gear_dicom_fixer/standard/2023a/json/module_info.json
fw_gear_dicom_fixer/standard/2023a/json/uid_info.json
fw_gear_dicom_fixer/standard/2023a/json/version
fw_gear_dicom_fixer-1.0.0.dist-info/METADATA
fw_gear_dicom_fixer-1.0.0.dist-info/WHEEL
fw_gear_dicom_fixer-1.0.0.dist-info/licenses/LICENSE
fw_gear_dicom_fixer-1.0.0.dist-info/RECORD
