Metadata-Version: 2.4
Name: fw-gear-dicom-fixer
Version: 1.0.0
Summary: This gear reports on the Dicom files data elements and optionally fixes or enhances the problematic ones, generating a new archive.
Project-URL: Repository, https://gitlab.com/flywheel-io/flywheel-apps/dicom-fixer
Author-email: Flywheel <support@flywheel.io>
License-Expression: MIT
License-File: LICENSE
Keywords: Dicom,Fixer,Flywheel,Gears
Classifier: Topic :: Scientific/Engineering :: Medical Science Apps.
Requires-Python: ~=3.10
Requires-Dist: flywheel-gear-toolkit<0.7,>=0.6
Requires-Dist: flywheel-sdk<17,>=16.0.0
Requires-Dist: fw-file<5,>=4.2.0
Requires-Dist: humanize<5,>=4.8.0
Requires-Dist: numpy~=2.1
Requires-Dist: psutil<7,>=6.0.0
Requires-Dist: pylibjpeg[all]~=2.0
